{"epidata": [{"geo_value": "ak", "signal": "deaths_cumulative_prop", "time_value": 20210601, "direction": null, "issue": 20210602, "lag": 1, "value": 49.4843106, "stderr": null, "sample_size": null}, {"geo_value": "al", "signal": "deaths_cumulative_prop", "time_value": 20210601, "direction": null, "issue": 20210602, "lag": 1, "value": 227.5255778, "stderr": null, "sample_size": null}, {"geo_value": "ar", "signal": "deaths_cumulative_prop", "time_value": 20210601, "direction": null, "issue": 20210602, "lag": 1, "value": 193.3193806, "stderr": null, "sample_size": null}, {"geo_value": "az", "signal": "deaths_cumulative_prop", "time_value": 20210601, "direction": null, "issue": 20210602, "lag": 1, "value": 242.185539, "stderr": null, "sample_size": null}, {"geo_value": "ca", "signal": "deaths_cumulative_prop", "time_value": 20210601, "direction": null, "issue": 20210602, "lag": 1, "value": 156.4174205, "stderr": null, "sample_size": null}, {"geo_value": "co", "signal": "deaths_cumulative_prop", "time_value": 20210601, "direction": null, "issue": 20210602, "lag": 1, "value": 114.2611851, "stderr": null, "sample_size": null}, {"geo_value": "ct", "signal": "deaths_cumulative_prop", "time_value": 20210601, "direction": null, "issue": 20210602, "lag": 1, "value": 231.2296317, "stderr": null, "sample_size": null}, {"geo_value": "dc", "signal": "deaths_cumulative_prop", "time_value": 20210601, "direction": null, "issue": 20210602, "lag": 1, "value": 160.6803552, "stderr": null, "sample_size": null}, {"geo_value": "de", "signal": "deaths_cumulative_prop", "time_value": 20210601, "direction": null, "issue": 20210602, "lag": 1, "value": 170.5752112, "stderr": null, "sample_size": null}, {"geo_value": "fl", "signal": "deaths_cumulative_prop", "time_value": 20210601, "direction": null, "issue": 20210602, "lag": 1, "value": 171.6614744, "stderr": null, "sample_size": null}, {"geo_value": "ga", "signal": "deaths_cumulative_prop", "time_value": 20210601, "direction": null, "issue": 20210602, "lag": 1, "value": 196.2623134, "stderr": null, "sample_size": null}, {"geo_value": "hi", "signal": "deaths_cumulative_prop", "time_value": 20210601, "direction": null, "issue": 20210602, "lag": 1, "value": 35.3139267, "stderr": null, "sample_size": null}, {"geo_value": "ia", "signal": "deaths_cumulative_prop", "time_value": 20210601, "direction": null, "issue": 20210602, "lag": 1, "value": 191.9133331, "stderr": null, "sample_size": null}, {"geo_value": "id", "signal": "deaths_cumulative_prop", "time_value": 20210601, "direction": null, "issue": 20210602, "lag": 1, "value": 116.9515379, "stderr": null, "sample_size": null}, {"geo_value": "il", "signal": "deaths_cumulative_prop", "time_value": 20210601, "direction": null, "issue": 20210602, "lag": 1, "value": 199.1268658, "stderr": null, "sample_size": null}, {"geo_value": "in", "signal": "deaths_cumulative_prop", "time_value": 20210601, "direction": null, "issue": 20210602, "lag": 1, "value": 202.4295407, "stderr": null, "sample_size": null}, {"geo_value": "ks", "signal": "deaths_cumulative_prop", "time_value": 20210601, "direction": null, "issue": 20210602, "lag": 1, "value": 174.2345659, "stderr": null, "sample_size": null}, {"geo_value": "ky", "signal": "deaths_cumulative_prop", "time_value": 20210601, "direction": null, "issue": 20210602, "lag": 1, "value": 158.18078, "stderr": null, "sample_size": null}, {"geo_value": "la", "signal": "deaths_cumulative_prop", "time_value": 20210601, "direction": null, "issue": 20210602, "lag": 1, "value": 227.8440387, "stderr": null, "sample_size": null}, {"geo_value": "ma", "signal": "deaths_cumulative_prop", "time_value": 20210601, "direction": null, "issue": 20210602, "lag": 1, "value": 259.4558174, "stderr": null, "sample_size": null}, {"geo_value": "md", "signal": "deaths_cumulative_prop", "time_value": 20210601, "direction": null, "issue": 20210602, "lag": 1, "value": 158.2948486, "stderr": null, "sample_size": null}, {"geo_value": "me", "signal": "deaths_cumulative_prop", "time_value": 20210601, "direction": null, "issue": 20210602, "lag": 1, "value": 61.3742475, "stderr": null, "sample_size": null}, {"geo_value": "mi", "signal": "deaths_cumulative_prop", "time_value": 20210601, "direction": null, "issue": 20210602, "lag": 1, "value": 204.1583253, "stderr": null, "sample_size": null}, {"geo_value": "mn", "signal": "deaths_cumulative_prop", "time_value": 20210601, "direction": null, "issue": 20210602, "lag": 1, "value": 131.6929899, "stderr": null, "sample_size": null}, {"geo_value": "mo", "signal": "deaths_cumulative_prop", "time_value": 20210601, "direction": null, "issue": 20210602, "lag": 1, "value": 147.9447091, "stderr": null, "sample_size": null}, {"geo_value": "ms", "signal": "deaths_cumulative_prop", "time_value": 20210601, "direction": null, "issue": 20210602, "lag": 1, "value": 245.8882267, "stderr": null, "sample_size": null}, {"geo_value": "mt", "signal": "deaths_cumulative_prop", "time_value": 20210601, "direction": null, "issue": 20210602, "lag": 1, "value": 150.9200227, "stderr": null, "sample_size": null}, {"geo_value": "nc", "signal": "deaths_cumulative_prop", "time_value": 20210601, "direction": null, "issue": 20210602, "lag": 1, "value": 124.9131872, "stderr": null, "sample_size": null}, {"geo_value": "nd", "signal": "deaths_cumulative_prop", "time_value": 20210601, "direction": null, "issue": 20210602, "lag": 1, "value": 198.4090533, "stderr": null, "sample_size": null}, {"geo_value": "ne", "signal": "deaths_cumulative_prop", "time_value": 20210601, "direction": null, "issue": 20210602, "lag": 1, "value": 115.2807474, "stderr": null, "sample_size": null}, {"geo_value": "nh", "signal": "deaths_cumulative_prop", "time_value": 20210601, "direction": null, "issue": 20210602, "lag": 1, "value": 99.7270744, "stderr": null, "sample_size": null}, {"geo_value": "nj", "signal": "deaths_cumulative_prop", "time_value": 20210601, "direction": null, "issue": 20210602, "lag": 1, "value": 294.5107006, "stderr": null, "sample_size": null}, {"geo_value": "nm", "signal": "deaths_cumulative_prop", "time_value": 20210601, "direction": null, "issue": 20210602, "lag": 1, "value": 203.3546846, "stderr": null, "sample_size": null}, {"geo_value": "nv", "signal": "deaths_cumulative_prop", "time_value": 20210601, "direction": null, "issue": 20210602, "lag": 1, "value": 181.4843144, "stderr": null, "sample_size": null}, {"geo_value": "ny", "signal": "deaths_cumulative_prop", "time_value": 20210601, "direction": null, "issue": 20210602, "lag": 1, "value": 272.1661088, "stderr": null, "sample_size": null}, {"geo_value": "oh", "signal": "deaths_cumulative_prop", "time_value": 20210601, "direction": null, "issue": 20210602, "lag": 1, "value": 169.9104294, "stderr": null, "sample_size": null}, {"geo_value": "ok", "signal": "deaths_cumulative_prop", "time_value": 20210601, "direction": null, "issue": 20210602, "lag": 1, "value": 184.2570997, "stderr": null, "sample_size": null}, {"geo_value": "or", "signal": "deaths_cumulative_prop", "time_value": 20210601, "direction": null, "issue": 20210602, "lag": 1, "value": 63.398927, "stderr": null, "sample_size": null}, {"geo_value": "pa", "signal": "deaths_cumulative_prop", "time_value": 20210601, "direction": null, "issue": 20210602, "lag": 1, "value": 212.5763426, "stderr": null, "sample_size": null}, {"geo_value": "ri", "signal": "deaths_cumulative_prop", "time_value": 20210601, "direction": null, "issue": 20210602, "lag": 1, "value": 256.0033832, "stderr": null, "sample_size": null}, {"geo_value": "sc", "signal": "deaths_cumulative_prop", "time_value": 20210601, "direction": null, "issue": 20210602, "lag": 1, "value": 189.0957626, "stderr": null, "sample_size": null}, {"geo_value": "sd", "signal": "deaths_cumulative_prop", "time_value": 20210601, "direction": null, "issue": 20210602, "lag": 1, "value": 227.6583407, "stderr": null, "sample_size": null}, {"geo_value": "tn", "signal": "deaths_cumulative_prop", "time_value": 20210601, "direction": null, "issue": 20210602, "lag": 1, "value": 182.3939469, "stderr": null, "sample_size": null}, {"geo_value": "tx", "signal": "deaths_cumulative_prop", "time_value": 20210601, "direction": null, "issue": 20210602, "lag": 1, "value": 173.8971132, "stderr": null, "sample_size": null}, {"geo_value": "ut", "signal": "deaths_cumulative_prop", "time_value": 20210601, "direction": null, "issue": 20210602, "lag": 1, "value": 71.8038103, "stderr": null, "sample_size": null}, {"geo_value": "va", "signal": "deaths_cumulative_prop", "time_value": 20210601, "direction": null, "issue": 20210602, "lag": 1, "value": 131.1460967, "stderr": null, "sample_size": null}, {"geo_value": "vt", "signal": "deaths_cumulative_prop", "time_value": 20210601, "direction": null, "issue": 20210602, "lag": 1, "value": 40.866105, "stderr": null, "sample_size": null}, {"geo_value": "wa", "signal": "deaths_cumulative_prop", "time_value": 20210601, "direction": null, "issue": 20210602, "lag": 1, "value": 76.0220794, "stderr": null, "sample_size": null}, {"geo_value": "wi", "signal": "deaths_cumulative_prop", "time_value": 20210601, "direction": null, "issue": 20210602, "lag": 1, "value": 121.8390797, "stderr": null, "sample_size": null}, {"geo_value": "wv", "signal": "deaths_cumulative_prop", "time_value": 20210601, "direction": null, "issue": 20210602, "lag": 1, "value": 156.0697867, "stderr": null, "sample_size": null}, {"geo_value": "wy", "signal": "deaths_cumulative_prop", "time_value": 20210601, "direction": null, "issue": 20210602, "lag": 1, "value": 124.4041129, "stderr": null, "sample_size": null}], "result": 1, "message": "success"}